circmimi/__init__.py
circmimi/ambiguous.py
circmimi/annotation.py
circmimi/bed.py
circmimi/blat.py
circmimi/circ.py
circmimi/circmimi.py
circmimi/miranda.py
circmimi/models.py
circmimi/rbp.py
circmimi/seq.py
circmimi/stats.py
circmimi/utils.py
circmimi/network/__init__.py
circmimi/network/network.py
circmimi/network/utils.py
circmimi/network/formats/__init__.py
circmimi/network/formats/xgmml.py
circmimi/reference/ENCORI.py
circmimi/reference/__init__.py
circmimi/reference/config.py
circmimi/reference/gendb.py
circmimi/reference/genmirdb.py
circmimi/reference/genref.py
circmimi/reference/mirbase.py
circmimi/reference/resource.py
circmimi/reference/species.py
circmimi/reference/utils.py
circmimi/scripts/__init__.py
circmimi/scripts/circmimi_tools.py
circmimi/scripts/mp_blat.py
circmimi/scripts/checkAA/__init__.py
circmimi/scripts/checkAA/checkAA_reads.py
circmimi/scripts/checkAA/get_flanking_seq.py
circmimi/scripts/get_RCS/RCS_filter.py
circmimi/scripts/get_RCS/__init__.py
circmimi/scripts/get_RCS/get_RCS.py
circmimi/scripts/get_RCS/get_RCS_summary.py
circmimi-0.18.5.dist-info/LICENSE
circmimi-0.18.5.dist-info/METADATA
circmimi-0.18.5.dist-info/WHEEL
circmimi-0.18.5.dist-info/entry_points.txt
circmimi-0.18.5.dist-info/top_level.txt
circmimi-0.18.5.dist-info/RECORD
