Metadata-Version: 2.1
Name: circmimi
Version: 0.18.5
Summary: A package for constructing CLIP-seq data-supported "circRNA - miRNA - mRNA" interactions
Home-page: https://github.com/TreesLab/CircMiMi
License: UNKNOWN
Platform: UNKNOWN
License-File: LICENSE
Requires-Dist: click (>=7.0)
Requires-Dist: sqlalchemy (>=1.3.8)
Requires-Dist: numpy (>=1.17.2)
Requires-Dist: pandas (>=0.25.1)
Requires-Dist: openpyxl
Requires-Dist: networkx (>=2.4)
Requires-Dist: lxml (>=4.5.0)
Requires-Dist: scipy (>=1.7.3)
Requires-Dist: statsmodels (>=0.13.1)
Requires-Dist: requests
Requires-Dist: tqdm
